simple_robotics_python_utils/__init__.py
simple_robotics_python_utils/common/io.py
simple_robotics_python_utils/common/logger.py
simple_robotics_python_utils/common/ros1bag_ros2bag_conversions.py
simple_robotics_python_utils/controllers/pid_controllers.py
simple_robotics_python_utils/cv/nms.py
simple_robotics_python_utils/pubsub/README.md
simple_robotics_python_utils/pubsub/discoverer.py
simple_robotics_python_utils/pubsub/pub_sub_utils.py
simple_robotics_python_utils/pubsub/shared_memory_pub_sub.py
simple_robotics_python_utils/pubsub/todo_tcp_pub_sub.py
simple_robotics_python_utils/sensors/motion_deblur.py
simple_robotics_python_utils/sensors/record_realsense_topics_in_bag.py
simple_robotics_python_utils/sensors/rpi_lidar_a1_visualization.py
simple_robotics_python_utils/sensors/visualize_pointcloud_open3d.py
simple_robotics_python_utils-1.1.0.dist-info/METADATA
simple_robotics_python_utils-1.1.0.dist-info/WHEEL
simple_robotics_python_utils-1.1.0.dist-info/RECORD
